xanthus/__init__.py
xanthus/datasets/__init__.py
xanthus/datasets/build.py
xanthus/datasets/core.py
xanthus/datasets/encoder.py
xanthus/datasets/movielens.py
xanthus/datasets/utils.py
xanthus/evaluate/__init__.py
xanthus/evaluate/metrics.py
xanthus/evaluate/utils.py
xanthus/models/__init__.py
xanthus/models/neural.py
xanthus/models/utils.py
xanthus/models/baseline/__init__.py
xanthus/models/baseline/mf.py
xanthus/models/baseline/pop_rank.py
xanthus/models/legacy/__init__.py
xanthus/models/legacy/base.py
xanthus/models/legacy/neural.py
xanthus/utils/__init__.py
xanthus/utils/benchmarking/__init__.py
xanthus/utils/benchmarking/core.py
xanthus/utils/benchmarking/managers.py
xanthus-0.1.0rc2.dist-info/LICENSE
xanthus-0.1.0rc2.dist-info/METADATA
xanthus-0.1.0rc2.dist-info/WHEEL
xanthus-0.1.0rc2.dist-info/top_level.txt
xanthus-0.1.0rc2.dist-info/RECORD
